trjtrypy/__init__.py
trjtrypy/basedists.py
trjtrypy/distances.py
trjtrypy/distsbase.py
trjtrypy/featureMappings.py
trjtrypy/version.py
trjtrypy/visualizations.py
trjtrypy-0.0.0.dist-info/LICENSE.txt
trjtrypy-0.0.0.dist-info/METADATA
trjtrypy-0.0.0.dist-info/WHEEL
trjtrypy-0.0.0.dist-info/top_level.txt
trjtrypy-0.0.0.dist-info/RECORD
