Metadata-Version: 2.1
Name: trjtrypy
Version: 0.0.0
Summary: Distance between trajectories
Home-page: https://github.com/GoldenStarCode/trjtrypy
Author: Hamed Khaiiate Ajami, Hasan Pourmahmood-Aghababa, Jeff M. Phillips
Author-email: goldenstarcodeteam@gmail.com
License: MIT license
Project-URL: Bug Reports, https://github.com/GoldenStarCode/trjtrypy/issues
Project-URL: Source, https://github.com/GoldenStarCode/trjtrypy/
Project-URL: Documentation, https://github.com/GoldenStarCode/trjtrypy/blob/main/README.rst
Platform: UNKNOWN
Classifier: Intended Audience :: Education
Classifier: Intended Audience :: Science/Research
Classifier: License :: OSI Approved :: MIT License
Classifier: Programming Language :: Python :: 3.7
Classifier: Programming Language :: Python :: 3.8
Classifier: Programming Language :: Python :: 3.9
Classifier: Topic :: Scientific/Engineering :: Mathematics
Classifier: Topic :: Scientific/Engineering :: Visualization
Requires-Python: >=3.7
License-File: LICENSE.txt
Requires-Dist: numpy (>=1.19.1)
Requires-Dist: scipy (>=1.6.3)
Requires-Dist: matplotlib (>=3.3.2)
